gs_interactive/__init__.py
gs_interactive/api_client.py
gs_interactive/api_response.py
gs_interactive/configuration.py
gs_interactive/exceptions.py
gs_interactive/py.typed
gs_interactive/rest.py
gs_interactive/api/__init__.py
gs_interactive/api/admin_service_graph_management_api.py
gs_interactive/api/admin_service_job_management_api.py
gs_interactive/api/admin_service_procedure_management_api.py
gs_interactive/api/admin_service_service_management_api.py
gs_interactive/api/graph_service_edge_management_api.py
gs_interactive/api/graph_service_vertex_management_api.py
gs_interactive/api/query_service_api.py
gs_interactive/client/__init__.py
gs_interactive/client/driver.py
gs_interactive/client/result.py
gs_interactive/client/session.py
gs_interactive/client/status.py
gs_interactive/client/generated/__init__.py
gs_interactive/client/generated/algebra_pb2.py
gs_interactive/client/generated/common_pb2.py
gs_interactive/client/generated/expr_pb2.py
gs_interactive/client/generated/physical_pb2.py
gs_interactive/client/generated/results_pb2.py
gs_interactive/client/generated/schema_pb2.py
gs_interactive/client/generated/stored_procedure_pb2.py
gs_interactive/client/generated/type_pb2.py
gs_interactive/models/__init__.py
gs_interactive/models/base_edge_type.py
gs_interactive/models/base_edge_type_vertex_type_pair_relations_inner.py
gs_interactive/models/base_edge_type_vertex_type_pair_relations_inner_x_csr_params.py
gs_interactive/models/base_property_meta.py
gs_interactive/models/base_vertex_type.py
gs_interactive/models/base_vertex_type_x_csr_params.py
gs_interactive/models/column_mapping.py
gs_interactive/models/create_edge_type.py
gs_interactive/models/create_graph_request.py
gs_interactive/models/create_graph_response.py
gs_interactive/models/create_graph_schema_request.py
gs_interactive/models/create_procedure_request.py
gs_interactive/models/create_procedure_response.py
gs_interactive/models/create_property_meta.py
gs_interactive/models/create_vertex_type.py
gs_interactive-0.3.dist-info/METADATA
gs_interactive-0.3.dist-info/WHEEL
gs_interactive-0.3.dist-info/top_level.txt
gs_interactive-0.3.dist-info/RECORD
